LICENSE
README.md
VERSION
requirements.txt
setup.py
texta_elastic/__init__.py
texta_elastic/aggregator.py
texta_elastic/core.py
texta_elastic/decorators.py
texta_elastic/document.py
texta_elastic/enums.py
texta_elastic/exceptions.py
texta_elastic/mapping_generator.py
texta_elastic/mapping_tools.py
texta_elastic/query.py
texta_elastic/searcher.py
texta_elastic/settings.py
texta_elastic/spam_detector.py
texta_elastic_tools.egg-info/PKG-INFO
texta_elastic_tools.egg-info/SOURCES.txt
texta_elastic_tools.egg-info/dependency_links.txt
texta_elastic_tools.egg-info/requires.txt
texta_elastic_tools.egg-info/top_level.txt