Metadata-Version: 2.1
Name: texta-elastic-tools
Version: 1.4.0
Summary: TEXTA Elasticsearch tools
Home-page: https://git.texta.ee/texta/texta-elastic-tools-python
Author: TEXTA
Author-email: info@texta.ee
License: GPLv3
Provides-Extra: mlp
License-File: LICENSE
